chessenv_c.abi3.so
fastchessenv_c.abi3.so
chessenv/__init__.py
chessenv/env.py
chessenv/libloader.py
chessenv/rep.py
chessenv/sfa.py
chessenv/lib/__init__.py
chessenv/lib/libmisterqueen.so
chessenv/lib/libtinycthread.so
fastchessenv/__init__.py
fastchessenv/env.py
fastchessenv/libloader.py
fastchessenv/rep.py
fastchessenv/setup_standalone.py
fastchessenv/sfa.py
fastchessenv/lib/__init__.py
fastchessenv/lib/libmisterqueen.so
fastchessenv/lib/libtinycthread.so
fastchessenv-0.1.1.dist-info/licenses/LICENSE
fastchessenv-0.1.1.dist-info/METADATA
fastchessenv-0.1.1.dist-info/WHEEL
fastchessenv-0.1.1.dist-info/top_level.txt
fastchessenv-0.1.1.dist-info/RECORD
