Metadata-Version: 2.4
Name: fastchessenv
Version: 0.1.1
Summary: Chess environment for reinforcement learning
Home-page: https://github.com/yourusername/chessenv
Author: Your Name
License-Expression: MIT
Project-URL: Homepage, https://github.com/yourusername/chessenv
Project-URL: BugTracker, https://github.com/yourusername/chessenv/issues
Keywords: chess,reinforcement-learning,openmp
Classifier: Development Status :: 4 - Beta
Classifier: Intended Audience :: Developers
Classifier: Intended Audience :: Science/Research
Classifier: Programming Language :: Python :: 3
Classifier: Programming Language :: Python :: 3.6
Classifier: Programming Language :: Python :: 3.7
Classifier: Programming Language :: Python :: 3.8
Classifier: Programming Language :: Python :: 3.9
Classifier: Topic :: Scientific/Engineering :: Artificial Intelligence
Requires-Python: >=3.6
License-File: LICENSE
Requires-Dist: cffi>=1.0.0
Requires-Dist: numpy
Requires-Dist: python-chess
Provides-Extra: dev
Requires-Dist: pytest>=7.0.1; extra == "dev"
Requires-Dist: open-spiel>=1.1.0; extra == "dev"
Dynamic: home-page
Dynamic: license-file
Dynamic: requires-python
